odoo/addons/cooperator_account_payment/__init__.py
odoo/addons/cooperator_account_payment/__manifest__.py
odoo/addons/cooperator_account_payment/models/__init__.py
odoo/addons/cooperator_account_payment/models/product_template.py
odoo/addons/cooperator_account_payment/models/subscription_request.py
odoo/addons/cooperator_account_payment/views/product_template_views.xml
odoo/addons/cooperator_account_payment/views/subscription_request_views.xml
odoo_addon_cooperator_account_payment-16.0.0.1.0.dist-info/METADATA
odoo_addon_cooperator_account_payment-16.0.0.1.0.dist-info/WHEEL
odoo_addon_cooperator_account_payment-16.0.0.1.0.dist-info/top_level.txt
odoo_addon_cooperator_account_payment-16.0.0.1.0.dist-info/RECORD
